pdf2image/__init__.py
pdf2image/exceptions.py
pdf2image/generators.py
pdf2image/parsers.py
pdf2image/pdf2image.py
pdf2image-1.16.2.dist-info/LICENSE
pdf2image-1.16.2.dist-info/METADATA
pdf2image-1.16.2.dist-info/WHEEL
pdf2image-1.16.2.dist-info/top_level.txt
pdf2image-1.16.2.dist-info/RECORD
