Metadata-Version: 2.1
Name: pdf2image
Version: 1.16.2
Summary: A wrapper around the pdftoppm and pdftocairo command line tools to convert PDF to a PIL Image list.
Home-page: https://github.com/Belval/pdf2image
Author: Edouard Belval
Author-email: edouard@belval.org
License: MIT
Keywords: pdf image png jpeg jpg convert
Platform: UNKNOWN
Classifier: Development Status :: 5 - Production/Stable
Classifier: Intended Audience :: Developers
Classifier: License :: OSI Approved :: MIT License
Classifier: Programming Language :: Python :: 3
Classifier: Programming Language :: Python :: 3.7
Classifier: Programming Language :: Python :: 3.8
Classifier: Programming Language :: Python :: 3.9
Classifier: Programming Language :: Python :: 3.10
License-File: LICENSE
